openqp.libs/libgfortran-8f1e9814.so.5.0.0
openqp.libs/libgomp-870cb1d0.so.1.0.0
openqp.libs/libmvec-2-8eb5c230.28.so
openqp.libs/libopenblas-r0-11edc3fa.3.15.so
openqp.libs/libquadmath-828275a7.so.0.0.0
oqp/__init__.py
oqp/pyoqp.py
oqp/include/oqp.h
oqp/lib/_oqp.abi3.so
oqp/lib/liboqp.so
oqp/library/__init__.py
oqp/library/frequency.py
oqp/library/guess.py
oqp/library/ints_1e.py
oqp/library/libdlfind.py
oqp/library/libscipy.py
oqp/library/project_basis.py
oqp/library/runfunc.py
oqp/library/set_basis.py
oqp/library/single_point.py
oqp/molden/__init__.py
oqp/molden/moldenreader.py
oqp/molden/moldenwriter.py
oqp/molecule/__init__.py
oqp/molecule/molecule.py
oqp/molecule/oqpdata.py
oqp/periodic_table/__init__.py
oqp/share/basis_sets/MIDI_huckel.basis
oqp/share/basis_sets/MINI_huckel.basis
oqp/share/examples/DFT/H2O_RHF-DFT_ENERGY.inp
oqp/share/examples/DFT/H2O_RHF-DFT_ENERGY.json
oqp/share/examples/DFT/H2O_RHF-DFT_GRADIENT.inp
oqp/share/examples/DFT/H2O_RHF-DFT_GRADIENT.json
oqp/share/examples/DFT/H2O_RHF-DFT_OPTIMIZE.json
oqp/share/examples/DFT/H2O_ROHF-DFT_ENERGY.inp
oqp/share/examples/DFT/H2O_ROHF-DFT_ENERGY.json
oqp/share/examples/DFT/H2O_ROHF-DFT_GRADIENT.inp
oqp/share/examples/DFT/H2O_ROHF-DFT_GRADIENT.json
oqp/share/examples/DFT/H2O_UHF-DFT_ENERGY.inp
oqp/share/examples/DFT/H2O_UHF-DFT_ENERGY.json
oqp/share/examples/DFT/H2O_UHF-DFT_GRADIENT.inp
oqp/share/examples/DFT/H2O_UHF-DFT_GRADIENT.json
oqp/share/examples/ECP/C2H4_BHHLYP-MRSFTDDFT_Energy.inp
oqp/share/examples/ECP/C2H4_BHHLYP-MRSFTDDFT_Energy.json
oqp/share/examples/ECP/C2H4_BHHLYP-MRSFTDDFT_Grad.inp
oqp/share/examples/ECP/C2H4_BHHLYP-MRSFTDDFT_Grad.json
oqp/share/examples/ECP/HBr_BHHLYP-MRSFTDDFT_ENERGY.inp
oqp/share/examples/ECP/HBr_BHHLYP-MRSFTDDFT_ENERGY.json
oqp/share/examples/ECP/HBr_RHF-DFT_ENERGY.inp
oqp/share/examples/ECP/HBr_RHF-DFT_ENERGY.json
oqp/share/examples/ECP/HBr_RHF-DFT_GRADIENT.inp
oqp/share/examples/ECP/HBr_RHF-DFT_GRADIENT.json
openqp-1.1.dist-info/METADATA
openqp-1.1.dist-info/WHEEL
openqp-1.1.dist-info/entry_points.txt
openqp-1.1.dist-info/RECORD
openqp-1.1.dist-info/licenses/LICENSE
